amiibo/__init__.py
amiibo/client.py
amiibo/errors.py
amiibo/httpclient.py
amiibo.py-0.1.0.dist-info/LICENSE
amiibo.py-0.1.0.dist-info/METADATA
amiibo.py-0.1.0.dist-info/WHEEL
amiibo.py-0.1.0.dist-info/top_level.txt
amiibo.py-0.1.0.dist-info/RECORD
