Metadata-Version: 2.1
Name: amiibo.py
Version: 0.1.0
Summary: An API Wrapper for amiiboapi.com written in Python
Home-page: https://github.com/XiehCanCode/amiibo.py
Author: Xieh
License: UNKNOWN
Platform: UNKNOWN
Classifier: Programming Language :: Python :: 3
Classifier: License :: OSI Approved :: MIT License
Classifier: Operating System :: OS Independent
Requires-Python: >=3.5.3
Requires-Dist: aiohttp
Requires-Dist: requests
